openai_messages_token_helper/__init__.py
openai_messages_token_helper/function_format.py
openai_messages_token_helper/images_helper.py
openai_messages_token_helper/message_builder.py
openai_messages_token_helper/model_helper.py
openai_messages_token_helper/py.typed
openai_messages_token_helper-0.1.13.dist-info/LICENSE
openai_messages_token_helper-0.1.13.dist-info/WHEEL
openai_messages_token_helper-0.1.13.dist-info/METADATA
openai_messages_token_helper-0.1.13.dist-info/RECORD
