Metadata-Version: 2.3
Name: openai-messages-token-helper
Version: 0.1.13
Summary: A helper library for estimating tokens used by messages sent through OpenAI Chat Completions API.
Author: Pamela Fox
Requires-Python: >=3.9
Classifier: License :: OSI Approved :: MIT License
Classifier: Programming Language :: Python
Classifier: Programming Language :: Python :: 3
Classifier: Programming Language :: Python :: 3.9
Classifier: Programming Language :: Python :: 3.10
Classifier: Programming Language :: Python :: 3.11
Classifier: Framework :: Pytest
Requires-Dist: openai
Requires-Dist: tiktoken
Requires-Dist: pillow
Requires-Dist: pytest ; extra == "dev"
Requires-Dist: pytest-cov ; extra == "dev"
Requires-Dist: pre-commit ; extra == "dev"
Requires-Dist: ruff ; extra == "dev"
Requires-Dist: black ; extra == "dev"
Requires-Dist: flit ; extra == "dev"
Requires-Dist: azure-identity ; extra == "dev"
Requires-Dist: python-dotenv ; extra == "dev"
Requires-Dist: mypy ; extra == "dev"
Project-URL: Home, https://github.com/pamelafox/openai-messages-token-helper
Provides-Extra: dev
